{
  "updated_at": "2026-07-07T17:36:13.471164+00:00",
  "error_count": 0,
  "quotes": {
    "NVDA": {
      "symbol": "NVDA",
      "name": "NVIDIA Corporation",
      "sector": "semiconductors",
      "price": 197.8,
      "change": 2.25,
      "change_pct": 1.15,
      "high": 198.41,
      "low": 191.14,
      "open": 193.12,
      "prev_close": 195.55,
      "updated_at": "2026-07-07T17:35:37.899954+00:00"
    },
    "AMD": {
      "symbol": "AMD",
      "name": "Advanced Micro Devices",
      "sector": "semiconductors",
      "price": 522.03,
      "change": -30.02,
      "change_pct": -5.44,
      "high": 527.03,
      "low": 503.11,
      "open": 527.03,
      "prev_close": 552.05,
      "updated_at": "2026-07-07T17:35:39.172141+00:00"
    },
    "INTC": {
      "symbol": "INTC",
      "name": "Intel Corporation",
      "sector": "semiconductors",
      "price": 111.08,
      "change": -11.12,
      "change_pct": -9.1,
      "high": 117.39,
      "low": 108.36,
      "open": 117.39,
      "prev_close": 122.2,
      "updated_at": "2026-07-07T17:35:40.443666+00:00"
    },
    "TSM": {
      "symbol": "TSM",
      "name": "Taiwan Semiconductor Manufacturing",
      "sector": "semiconductors",
      "price": 437.29,
      "change": -14.5,
      "change_pct": -3.21,
      "high": 439.8,
      "low": 428.11,
      "open": 438.02,
      "prev_close": 451.79,
      "updated_at": "2026-07-07T17:35:41.715330+00:00"
    },
    "GOOGL": {
      "symbol": "GOOGL",
      "name": "Alphabet Inc.",
      "sector": "hyperscaler",
      "price": 369.72,
      "change": 3.26,
      "change_pct": 0.89,
      "high": 373.16,
      "low": 366.53,
      "open": 367.49,
      "prev_close": 366.46,
      "updated_at": "2026-07-07T17:35:42.990313+00:00"
    },
    "MSFT": {
      "symbol": "MSFT",
      "name": "Microsoft Corporation",
      "sector": "hyperscaler",
      "price": 392.84,
      "change": 6.1,
      "change_pct": 1.58,
      "high": 395.57,
      "low": 388.52,
      "open": 390.89,
      "prev_close": 386.74,
      "updated_at": "2026-07-07T17:35:44.265729+00:00"
    },
    "META": {
      "symbol": "META",
      "name": "Meta Platforms",
      "sector": "hyperscaler",
      "price": 608.05,
      "change": 7.76,
      "change_pct": 1.29,
      "high": 615.99,
      "low": 603.58,
      "open": 603.58,
      "prev_close": 600.29,
      "updated_at": "2026-07-07T17:35:45.537597+00:00"
    },
    "AMZN": {
      "symbol": "AMZN",
      "name": "Amazon.com Inc.",
      "sector": "hyperscaler",
      "price": 245.72,
      "change": 1.56,
      "change_pct": 0.64,
      "high": 248.93,
      "low": 242.7,
      "open": 245.74,
      "prev_close": 244.16,
      "updated_at": "2026-07-07T17:35:46.808869+00:00"
    },
    "AAPL": {
      "symbol": "AAPL",
      "name": "Apple Inc.",
      "sector": "hyperscaler",
      "price": 312.84,
      "change": 0.18,
      "change_pct": 0.06,
      "high": 315.48,
      "low": 310.15,
      "open": 314.23,
      "prev_close": 312.66,
      "updated_at": "2026-07-07T17:35:48.084987+00:00"
    },
    "ORCL": {
      "symbol": "ORCL",
      "name": "Oracle Corporation",
      "sector": "enterprise_ai",
      "price": 140.74,
      "change": -3.02,
      "change_pct": -2.1,
      "high": 145.56,
      "low": 137.55,
      "open": 143.72,
      "prev_close": 143.76,
      "updated_at": "2026-07-07T17:35:49.356835+00:00"
    },
    "PLTR": {
      "symbol": "PLTR",
      "name": "Palantir Technologies",
      "sector": "enterprise_ai",
      "price": 138.04,
      "change": 5.5,
      "change_pct": 4.15,
      "high": 138.12,
      "low": 131.46,
      "open": 133.54,
      "prev_close": 132.54,
      "updated_at": "2026-07-07T17:35:50.628851+00:00"
    },
    "SMCI": {
      "symbol": "SMCI",
      "name": "Super Micro Computer",
      "sector": "infrastructure",
      "price": 26.45,
      "change": -0.74,
      "change_pct": -2.72,
      "high": 26.98,
      "low": 25.41,
      "open": 26.7,
      "prev_close": 27.19,
      "updated_at": "2026-07-07T17:35:51.901393+00:00"
    },
    "AVGO": {
      "symbol": "AVGO",
      "name": "Broadcom Inc.",
      "sector": "semiconductors",
      "price": 372.31,
      "change": -1.59,
      "change_pct": -0.43,
      "high": 372.5,
      "low": 362.01,
      "open": 367.88,
      "prev_close": 373.9,
      "updated_at": "2026-07-07T17:35:53.178423+00:00"
    },
    "ARM": {
      "symbol": "ARM",
      "name": "Arm Holdings",
      "sector": "semiconductors",
      "price": 304.31,
      "change": -17.93,
      "change_pct": -5.56,
      "high": 314.9,
      "low": 297.05,
      "open": 309.67,
      "prev_close": 322.24,
      "updated_at": "2026-07-07T17:35:54.449736+00:00"
    },
    "ASML": {
      "symbol": "ASML",
      "name": "ASML Holding",
      "sector": "semiconductor_equipment",
      "price": 1758.34,
      "change": -66.73,
      "change_pct": -3.66,
      "high": 1762.49,
      "low": 1717.31,
      "open": 1762.49,
      "prev_close": 1825.07,
      "updated_at": "2026-07-07T17:35:55.721771+00:00"
    },
    "AMAT": {
      "symbol": "AMAT",
      "name": "Applied Materials",
      "sector": "semiconductor_equipment",
      "price": 551.64,
      "change": -41.15,
      "change_pct": -6.94,
      "high": 558.28,
      "low": 527.63,
      "open": 557.59,
      "prev_close": 592.79,
      "updated_at": "2026-07-07T17:35:56.993032+00:00"
    },
    "LRCX": {
      "symbol": "LRCX",
      "name": "Lam Research",
      "sector": "semiconductor_equipment",
      "price": 326.31,
      "change": -23.89,
      "change_pct": -6.82,
      "high": 330.75,
      "low": 313.1,
      "open": 330.58,
      "prev_close": 350.2,
      "updated_at": "2026-07-07T17:35:58.264732+00:00"
    },
    "MU": {
      "symbol": "MU",
      "name": "Micron Technology",
      "sector": "semiconductors",
      "price": 933.98,
      "change": -50.77,
      "change_pct": -5.16,
      "high": 938.76,
      "low": 891.66,
      "open": 931.16,
      "prev_close": 984.75,
      "updated_at": "2026-07-07T17:35:59.536296+00:00"
    },
    "IBM": {
      "symbol": "IBM",
      "name": "IBM",
      "sector": "enterprise_ai",
      "price": 311.36,
      "change": 11.84,
      "change_pct": 3.95,
      "high": 311.71,
      "low": 300.49,
      "open": 305.66,
      "prev_close": 299.52,
      "updated_at": "2026-07-07T17:36:00.811197+00:00"
    },
    "CRM": {
      "symbol": "CRM",
      "name": "Salesforce Inc.",
      "sector": "enterprise_ai",
      "price": 171.36,
      "change": 5.71,
      "change_pct": 3.45,
      "high": 172.38,
      "low": 167.68,
      "open": 169.22,
      "prev_close": 165.65,
      "updated_at": "2026-07-07T17:36:02.087197+00:00"
    },
    "NOW": {
      "symbol": "NOW",
      "name": "ServiceNow",
      "sector": "enterprise_ai",
      "price": 112.63,
      "change": 4.7,
      "change_pct": 4.35,
      "high": 113.79,
      "low": 109.04,
      "open": 111.55,
      "prev_close": 107.93,
      "updated_at": "2026-07-07T17:36:03.358644+00:00"
    },
    "SNOW": {
      "symbol": "SNOW",
      "name": "Snowflake Inc.",
      "sector": "enterprise_ai",
      "price": 268.65,
      "change": 6.56,
      "change_pct": 2.5,
      "high": 270.95,
      "low": 262.59,
      "open": 266.35,
      "prev_close": 262.09,
      "updated_at": "2026-07-07T17:36:04.632747+00:00"
    },
    "PATH": {
      "symbol": "PATH",
      "name": "UiPath Inc.",
      "sector": "enterprise_ai",
      "price": 11.92,
      "change": 0.09,
      "change_pct": 0.76,
      "high": 12.31,
      "low": 11.56,
      "open": 12.19,
      "prev_close": 11.83,
      "updated_at": "2026-07-07T17:36:05.905964+00:00"
    },
    "AI": {
      "symbol": "AI",
      "name": "C3.ai Inc.",
      "sector": "enterprise_ai",
      "price": 9.17,
      "change": -0.11,
      "change_pct": -1.19,
      "high": 9.5,
      "low": 8.89,
      "open": 9.36,
      "prev_close": 9.28,
      "updated_at": "2026-07-07T17:36:07.178897+00:00"
    },
    "BBAI": {
      "symbol": "BBAI",
      "name": "BigBear.ai",
      "sector": "enterprise_ai",
      "price": 3.58,
      "change": 0.0,
      "change_pct": 0.0,
      "high": 3.61,
      "low": 3.38,
      "open": 3.56,
      "prev_close": 3.58,
      "updated_at": "2026-07-07T17:36:08.451882+00:00"
    },
    "CRWV": {
      "symbol": "CRWV",
      "name": "CoreWeave Inc.",
      "sector": "infrastructure",
      "price": 83.49,
      "change": -2.97,
      "change_pct": -3.44,
      "high": 85.31,
      "low": 79.46,
      "open": 84.45,
      "prev_close": 86.46,
      "updated_at": "2026-07-07T17:36:09.723183+00:00"
    },
    "BIDU": {
      "symbol": "BIDU",
      "name": "Baidu Inc.",
      "sector": "hyperscaler",
      "price": 112.32,
      "change": -2.07,
      "change_pct": -1.81,
      "high": 114.9,
      "low": 111.27,
      "open": 112.73,
      "prev_close": 114.39,
      "updated_at": "2026-07-07T17:36:10.999445+00:00"
    },
    "BABA": {
      "symbol": "BABA",
      "name": "Alibaba Group",
      "sector": "hyperscaler",
      "price": 98.22,
      "change": 0.31,
      "change_pct": 0.32,
      "high": 99.74,
      "low": 97.39,
      "open": 97.8,
      "prev_close": 97.91,
      "updated_at": "2026-07-07T17:36:12.270887+00:00"
    }
  }
}