{
  "updated_at": "2026-07-23T15:00:41.872741+00:00",
  "error_count": 0,
  "quotes": {
    "NVDA": {
      "symbol": "NVDA",
      "name": "NVIDIA Corporation",
      "sector": "semiconductors",
      "price": 207.42,
      "change": -4.64,
      "change_pct": -2.19,
      "high": 210.87,
      "low": 207.2,
      "open": 210.2,
      "prev_close": 212.06,
      "updated_at": "2026-07-23T15:00:05.868714+00:00"
    },
    "AMD": {
      "symbol": "AMD",
      "name": "Advanced Micro Devices",
      "sector": "semiconductors",
      "price": 544.84,
      "change": -7.49,
      "change_pct": -1.36,
      "high": 558.16,
      "low": 542.01,
      "open": 546.89,
      "prev_close": 552.33,
      "updated_at": "2026-07-23T15:00:07.138980+00:00"
    },
    "INTC": {
      "symbol": "INTC",
      "name": "Intel Corporation",
      "sector": "semiconductors",
      "price": 101.82,
      "change": -0.8,
      "change_pct": -0.78,
      "high": 104.18,
      "low": 100.11,
      "open": 102.0,
      "prev_close": 102.62,
      "updated_at": "2026-07-23T15:00:08.407932+00:00"
    },
    "TSM": {
      "symbol": "TSM",
      "name": "Taiwan Semiconductor Manufacturing",
      "sector": "semiconductors",
      "price": 416.37,
      "change": -4.84,
      "change_pct": -1.15,
      "high": 420.84,
      "low": 412.51,
      "open": 415.84,
      "prev_close": 421.21,
      "updated_at": "2026-07-23T15:00:09.800073+00:00"
    },
    "GOOGL": {
      "symbol": "GOOGL",
      "name": "Alphabet Inc.",
      "sector": "hyperscaler",
      "price": 317.32,
      "change": -24.77,
      "change_pct": -7.24,
      "high": 326.57,
      "low": 316.93,
      "open": 326.57,
      "prev_close": 342.09,
      "updated_at": "2026-07-23T15:00:11.071729+00:00"
    },
    "MSFT": {
      "symbol": "MSFT",
      "name": "Microsoft Corporation",
      "sector": "hyperscaler",
      "price": 378.88,
      "change": -11.46,
      "change_pct": -2.94,
      "high": 391.78,
      "low": 378.84,
      "open": 388.54,
      "prev_close": 390.34,
      "updated_at": "2026-07-23T15:00:12.340746+00:00"
    },
    "META": {
      "symbol": "META",
      "name": "Meta Platforms",
      "sector": "hyperscaler",
      "price": 602.7,
      "change": -24.47,
      "change_pct": -3.9,
      "high": 614.65,
      "low": 602.38,
      "open": 614.03,
      "prev_close": 627.17,
      "updated_at": "2026-07-23T15:00:13.765745+00:00"
    },
    "AMZN": {
      "symbol": "AMZN",
      "name": "Amazon.com Inc.",
      "sector": "hyperscaler",
      "price": 232.41,
      "change": -12.44,
      "change_pct": -5.08,
      "high": 239.03,
      "low": 232.33,
      "open": 239.03,
      "prev_close": 244.85,
      "updated_at": "2026-07-23T15:00:15.035360+00:00"
    },
    "AAPL": {
      "symbol": "AAPL",
      "name": "Apple Inc.",
      "sector": "hyperscaler",
      "price": 321.18,
      "change": -4.71,
      "change_pct": -1.45,
      "high": 323.3,
      "low": 319.35,
      "open": 323.17,
      "prev_close": 325.89,
      "updated_at": "2026-07-23T15:00:16.310092+00:00"
    },
    "ORCL": {
      "symbol": "ORCL",
      "name": "Oracle Corporation",
      "sector": "enterprise_ai",
      "price": 121.42,
      "change": -4.42,
      "change_pct": -3.51,
      "high": 124.7,
      "low": 121.34,
      "open": 123.96,
      "prev_close": 125.84,
      "updated_at": "2026-07-23T15:00:17.578344+00:00"
    },
    "PLTR": {
      "symbol": "PLTR",
      "name": "Palantir Technologies",
      "sector": "enterprise_ai",
      "price": 121.46,
      "change": -3.11,
      "change_pct": -2.5,
      "high": 126.4,
      "low": 121.41,
      "open": 125.57,
      "prev_close": 124.57,
      "updated_at": "2026-07-23T15:00:18.856239+00:00"
    },
    "SMCI": {
      "symbol": "SMCI",
      "name": "Super Micro Computer",
      "sector": "infrastructure",
      "price": 31.34,
      "change": 0.78,
      "change_pct": 2.55,
      "high": 32.27,
      "low": 30.18,
      "open": 30.48,
      "prev_close": 30.56,
      "updated_at": "2026-07-23T15:00:20.127785+00:00"
    },
    "AVGO": {
      "symbol": "AVGO",
      "name": "Broadcom Inc.",
      "sector": "semiconductors",
      "price": 390.48,
      "change": -6.33,
      "change_pct": -1.6,
      "high": 397.61,
      "low": 389.37,
      "open": 393.9,
      "prev_close": 396.81,
      "updated_at": "2026-07-23T15:00:21.396262+00:00"
    },
    "ARM": {
      "symbol": "ARM",
      "name": "Arm Holdings",
      "sector": "semiconductors",
      "price": 278.0,
      "change": -5.4,
      "change_pct": -1.91,
      "high": 283.66,
      "low": 275.0,
      "open": 278.77,
      "prev_close": 283.4,
      "updated_at": "2026-07-23T15:00:22.690430+00:00"
    },
    "ASML": {
      "symbol": "ASML",
      "name": "ASML Holding",
      "sector": "semiconductor_equipment",
      "price": 1802.07,
      "change": 0.21,
      "change_pct": 0.01,
      "high": 1823.58,
      "low": 1780.24,
      "open": 1794.56,
      "prev_close": 1801.86,
      "updated_at": "2026-07-23T15:00:23.964748+00:00"
    },
    "AMAT": {
      "symbol": "AMAT",
      "name": "Applied Materials",
      "sector": "semiconductor_equipment",
      "price": 568.08,
      "change": 14.16,
      "change_pct": 2.56,
      "high": 576.49,
      "low": 547.39,
      "open": 549.89,
      "prev_close": 553.92,
      "updated_at": "2026-07-23T15:00:25.245098+00:00"
    },
    "LRCX": {
      "symbol": "LRCX",
      "name": "Lam Research",
      "sector": "semiconductor_equipment",
      "price": 321.13,
      "change": 1.84,
      "change_pct": 0.58,
      "high": 325.88,
      "low": 314.35,
      "open": 315.98,
      "prev_close": 319.29,
      "updated_at": "2026-07-23T15:00:26.567695+00:00"
    },
    "MU": {
      "symbol": "MU",
      "name": "Micron Technology",
      "sector": "semiconductors",
      "price": 990.58,
      "change": 31.1,
      "change_pct": 3.24,
      "high": 1001.42,
      "low": 964.4,
      "open": 972.91,
      "prev_close": 959.48,
      "updated_at": "2026-07-23T15:00:27.841102+00:00"
    },
    "IBM": {
      "symbol": "IBM",
      "name": "IBM",
      "sector": "enterprise_ai",
      "price": 205.91,
      "change": 0.14,
      "change_pct": 0.07,
      "high": 206.7,
      "low": 199.19,
      "open": 202.64,
      "prev_close": 205.77,
      "updated_at": "2026-07-23T15:00:29.131282+00:00"
    },
    "CRM": {
      "symbol": "CRM",
      "name": "Salesforce Inc.",
      "sector": "enterprise_ai",
      "price": 155.73,
      "change": -7.27,
      "change_pct": -4.46,
      "high": 165.88,
      "low": 155.6,
      "open": 165.05,
      "prev_close": 163.0,
      "updated_at": "2026-07-23T15:00:30.400459+00:00"
    },
    "NOW": {
      "symbol": "NOW",
      "name": "ServiceNow",
      "sector": "enterprise_ai",
      "price": 94.45,
      "change": -1.01,
      "change_pct": -1.06,
      "high": 100.25,
      "low": 93.81,
      "open": 100.0,
      "prev_close": 95.46,
      "updated_at": "2026-07-23T15:00:31.672060+00:00"
    },
    "SNOW": {
      "symbol": "SNOW",
      "name": "Snowflake Inc.",
      "sector": "enterprise_ai",
      "price": 264.58,
      "change": -3.22,
      "change_pct": -1.2,
      "high": 277.51,
      "low": 263.65,
      "open": 273.85,
      "prev_close": 267.8,
      "updated_at": "2026-07-23T15:00:33.005137+00:00"
    },
    "PATH": {
      "symbol": "PATH",
      "name": "UiPath Inc.",
      "sector": "enterprise_ai",
      "price": 10.51,
      "change": -0.19,
      "change_pct": -1.78,
      "high": 10.96,
      "low": 10.46,
      "open": 10.77,
      "prev_close": 10.7,
      "updated_at": "2026-07-23T15:00:34.275515+00:00"
    },
    "AI": {
      "symbol": "AI",
      "name": "C3.ai Inc.",
      "sector": "enterprise_ai",
      "price": 8.0,
      "change": -0.19,
      "change_pct": -2.32,
      "high": 8.18,
      "low": 7.93,
      "open": 8.18,
      "prev_close": 8.19,
      "updated_at": "2026-07-23T15:00:35.558878+00:00"
    },
    "BBAI": {
      "symbol": "BBAI",
      "name": "BigBear.ai",
      "sector": "enterprise_ai",
      "price": 2.89,
      "change": 0.01,
      "change_pct": 0.35,
      "high": 2.98,
      "low": 2.83,
      "open": 2.84,
      "prev_close": 2.88,
      "updated_at": "2026-07-23T15:00:36.856426+00:00"
    },
    "CRWV": {
      "symbol": "CRWV",
      "name": "CoreWeave Inc.",
      "sector": "infrastructure",
      "price": 82.12,
      "change": -0.52,
      "change_pct": -0.63,
      "high": 85.2,
      "low": 80.56,
      "open": 82.65,
      "prev_close": 82.64,
      "updated_at": "2026-07-23T15:00:38.125682+00:00"
    },
    "BIDU": {
      "symbol": "BIDU",
      "name": "Baidu Inc.",
      "sector": "hyperscaler",
      "price": 106.69,
      "change": -0.83,
      "change_pct": -0.77,
      "high": 108.21,
      "low": 106.56,
      "open": 107.7,
      "prev_close": 107.52,
      "updated_at": "2026-07-23T15:00:39.404085+00:00"
    },
    "BABA": {
      "symbol": "BABA",
      "name": "Alibaba Group",
      "sector": "hyperscaler",
      "price": 114.6,
      "change": -1.96,
      "change_pct": -1.68,
      "high": 116.41,
      "low": 114.44,
      "open": 115.76,
      "prev_close": 116.56,
      "updated_at": "2026-07-23T15:00:40.672466+00:00"
    }
  }
}